{
  "class_counts": {
    "1m": 57,
    "1p": 29,
    "1s": 10,
    "1z": 20,
    "2m": 68,
    "2p": 46,
    "2s": 28,
    "2z": 26,
    "3m": 41,
    "3p": 63,
    "3s": 30,
    "3z": 20,
    "4m": 26,
    "4p": 51,
    "4s": 24,
    "4z": 14,
    "5m": 44,
    "5p": 30,
    "5s": 36,
    "5z": 31,
    "6m": 107,
    "6p": 14,
    "6s": 44,
    "6z": 58,
    "7m": 58,
    "7p": 46,
    "7s": 55,
    "7z": 69,
    "8m": 28,
    "8p": 79,
    "8s": 62,
    "9m": 30,
    "9p": 39,
    "9s": 60
  },
  "n_classes": 34,
  "min_samples_per_class": 10,
  "trusted": true,
  "trusted_rule": {
    "min_classes": 34,
    "min_samples_per_class": 5
  }
}